{"comment": "2 contexts: both are shared with phase 3", "trials": [{"images": [{"path": "page8-169.svg"}, {"path": "page3-180.svg"}, {"path": "page8-21.svg"}, {"path": "page4-16.svg"}, {"path": "page1-34.svg"}, {"path": "page4-66.svg"}, {"path": "page7-73.svg"}, {"path": "page4-157.svg"}, {"path": "page8-236.svg"}, {"path": "page4-156.svg"}], "target": "page8-169.svg", "target_snd_class": "high", "block": 0, "target_controled": false, "tangrams_order": [[4, 3, 8, 5, 6, 9, 0, 7, 1, 2], [7, 6, 4, 3, 2, 0, 1, 9, 8, 5]], "roles": ["speaker", "listener"], "chat_mode": "single-utterance-unidirectional"}, {"images": [{"path": "page8-169.svg"}, {"path": "page3-180.svg"}, {"path": "page8-21.svg"}, {"path": "page4-16.svg"}, {"path": "page1-34.svg"}, {"path": "page4-66.svg"}, {"path": "page7-73.svg"}, {"path": "page4-157.svg"}, {"path": "page8-236.svg"}, {"path": "page4-156.svg"}], "target": "page3-180.svg", "target_snd_class": "high", "block": 0, "target_controled": false, "tangrams_order": [[7, 6, 4, 3, 2, 0, 1, 9, 8, 5], [4, 3, 8, 5, 6, 9, 0, 7, 1, 2]], "roles": ["listener", "speaker"], "chat_mode": "single-utterance-unidirectional"}, {"images": [{"path": "page8-169.svg"}, {"path": "page3-180.svg"}, {"path": "page8-21.svg"}, {"path": "page4-16.svg"}, {"path": "page1-34.svg"}, {"path": "page4-66.svg"}, {"path": "page7-73.svg"}, {"path": "page4-157.svg"}, {"path": "page8-236.svg"}, {"path": "page4-156.svg"}], "target": "page8-21.svg", "target_snd_class": "low", "block": 0, "target_controled": false, "tangrams_order": [[4, 3, 8, 5, 6, 9, 0, 7, 1, 2], [7, 6, 4, 3, 2, 0, 1, 9, 8, 5]], "roles": ["speaker", "listener"], "chat_mode": "single-utterance-unidirectional"}, {"images": [{"path": "page8-169.svg"}, {"path": "page3-180.svg"}, {"path": "page8-21.svg"}, {"path": "page4-16.svg"}, {"path": "page1-34.svg"}, {"path": "page4-66.svg"}, {"path": "page7-73.svg"}, {"path": "page4-157.svg"}, {"path": "page8-236.svg"}, {"path": "page4-156.svg"}], "target": "page4-16.svg", "target_snd_class": "low", "block": 0, "target_controled": false, "tangrams_order": [[7, 6, 4, 3, 2, 0, 1, 9, 8, 5], [4, 3, 8, 5, 6, 9, 0, 7, 1, 2]], "roles": ["listener", "speaker"], "chat_mode": "single-utterance-unidirectional"}, {"images": [{"path": "page8-169.svg"}, {"path": "page3-180.svg"}, {"path": "page8-21.svg"}, {"path": "page4-16.svg"}, {"path": "page1-34.svg"}, {"path": "page4-66.svg"}, {"path": "page7-73.svg"}, {"path": "page4-157.svg"}, {"path": "page8-236.svg"}, {"path": "page4-156.svg"}], "target": "page1-34.svg", "target_snd_class": "high", "block": 0, "target_controled": false, "tangrams_order": [[4, 3, 8, 5, 6, 9, 0, 7, 1, 2], [7, 6, 4, 3, 2, 0, 1, 9, 8, 5]], "roles": ["speaker", "listener"], "chat_mode": "single-utterance-unidirectional"}, {"images": [{"path": "page8-169.svg"}, {"path": "page3-180.svg"}, {"path": "page8-21.svg"}, {"path": "page4-16.svg"}, {"path": "page1-34.svg"}, {"path": "page4-66.svg"}, {"path": "page7-73.svg"}, {"path": "page4-157.svg"}, {"path": "page8-236.svg"}, {"path": "page4-156.svg"}], "target": "page4-66.svg", "target_snd_class": "high", "block": 0, "target_controled": false, "tangrams_order": [[7, 6, 4, 3, 2, 0, 1, 9, 8, 5], [4, 3, 8, 5, 6, 9, 0, 7, 1, 2]], "roles": ["listener", "speaker"], "chat_mode": "single-utterance-unidirectional"}, {"images": [{"path": "page8-169.svg"}, {"path": "page3-180.svg"}, {"path": "page8-21.svg"}, {"path": "page4-16.svg"}, {"path": "page1-34.svg"}, {"path": "page4-66.svg"}, {"path": "page7-73.svg"}, {"path": "page4-157.svg"}, {"path": "page8-236.svg"}, {"path": "page4-156.svg"}], "target": "page7-73.svg", "target_snd_class": "low", "block": 0, "target_controled": false, "tangrams_order": [[4, 3, 8, 5, 6, 9, 0, 7, 1, 2], [7, 6, 4, 3, 2, 0, 1, 9, 8, 5]], "roles": ["speaker", "listener"], "chat_mode": "single-utterance-unidirectional"}, {"images": [{"path": "page8-169.svg"}, {"path": "page3-180.svg"}, {"path": "page8-21.svg"}, {"path": "page4-16.svg"}, {"path": "page1-34.svg"}, {"path": "page4-66.svg"}, {"path": "page7-73.svg"}, {"path": "page4-157.svg"}, {"path": "page8-236.svg"}, {"path": "page4-156.svg"}], "target": "page4-157.svg", "target_snd_class": "high", "block": 0, "target_controled": false, "tangrams_order": [[7, 6, 4, 3, 2, 0, 1, 9, 8, 5], [4, 3, 8, 5, 6, 9, 0, 7, 1, 2]], "roles": ["listener", "speaker"], "chat_mode": "single-utterance-unidirectional"}, {"images": [{"path": "page8-169.svg"}, {"path": "page3-180.svg"}, {"path": "page8-21.svg"}, {"path": "page4-16.svg"}, {"path": "page1-34.svg"}, {"path": "page4-66.svg"}, {"path": "page7-73.svg"}, {"path": "page4-157.svg"}, {"path": "page8-236.svg"}, {"path": "page4-156.svg"}], "target": "page8-236.svg", "target_snd_class": "high", "block": 0, "target_controled": false, "tangrams_order": [[4, 3, 8, 5, 6, 9, 0, 7, 1, 2], [7, 6, 4, 3, 2, 0, 1, 9, 8, 5]], "roles": ["speaker", "listener"], "chat_mode": "single-utterance-unidirectional"}, {"images": [{"path": "page8-169.svg"}, {"path": "page3-180.svg"}, {"path": "page8-21.svg"}, {"path": "page4-16.svg"}, {"path": "page1-34.svg"}, {"path": "page4-66.svg"}, {"path": "page7-73.svg"}, {"path": "page4-157.svg"}, {"path": "page8-236.svg"}, {"path": "page4-156.svg"}], "target": "page4-156.svg", "target_snd_class": "low", "block": 0, "target_controled": false, "tangrams_order": [[7, 6, 4, 3, 2, 0, 1, 9, 8, 5], [4, 3, 8, 5, 6, 9, 0, 7, 1, 2]], "roles": ["listener", "speaker"], "chat_mode": "single-utterance-unidirectional"}, {"images": [{"path": "page4-215.svg"}, {"path": "page6-160.svg"}, {"path": "page8-21.svg"}, {"path": "page6-172.svg"}, {"path": "page4-214.svg"}, {"path": "page7-245.svg"}, {"path": "page6-121.svg"}, {"path": "page6-149.svg"}, {"path": "page8-215.svg"}, {"path": "page4-11.svg"}], "target": "page4-215.svg", "target_snd_class": "high", "block": 0, "target_controled": false, "tangrams_order": [[9, 1, 8, 3, 6, 7, 4, 2, 0, 5], [2, 5, 1, 8, 4, 7, 6, 3, 0, 9]], "roles": ["speaker", "listener"], "chat_mode": "single-utterance-unidirectional"}, {"images": [{"path": "page4-215.svg"}, {"path": "page6-160.svg"}, {"path": "page8-21.svg"}, {"path": "page6-172.svg"}, {"path": "page4-214.svg"}, {"path": "page7-245.svg"}, {"path": "page6-121.svg"}, {"path": "page6-149.svg"}, {"path": "page8-215.svg"}, {"path": "page4-11.svg"}], "target": "page6-160.svg", "target_snd_class": "low", "block": 0, "target_controled": false, "tangrams_order": [[2, 5, 1, 8, 4, 7, 6, 3, 0, 9], [9, 1, 8, 3, 6, 7, 4, 2, 0, 5]], "roles": ["listener", "speaker"], "chat_mode": "single-utterance-unidirectional"}, {"images": [{"path": "page4-215.svg"}, {"path": "page6-160.svg"}, {"path": "page8-21.svg"}, {"path": "page6-172.svg"}, {"path": "page4-214.svg"}, {"path": "page7-245.svg"}, {"path": "page6-121.svg"}, {"path": "page6-149.svg"}, {"path": "page8-215.svg"}, {"path": "page4-11.svg"}], "target": "page8-21.svg", "target_snd_class": "low", "block": 0, "target_controled": false, "tangrams_order": [[9, 1, 8, 3, 6, 7, 4, 2, 0, 5], [2, 5, 1, 8, 4, 7, 6, 3, 0, 9]], "roles": ["speaker", "listener"], "chat_mode": "single-utterance-unidirectional"}, {"images": [{"path": "page4-215.svg"}, {"path": "page6-160.svg"}, {"path": "page8-21.svg"}, {"path": "page6-172.svg"}, {"path": "page4-214.svg"}, {"path": "page7-245.svg"}, {"path": "page6-121.svg"}, {"path": "page6-149.svg"}, {"path": "page8-215.svg"}, {"path": "page4-11.svg"}], "target": "page6-172.svg", "target_snd_class": "low", "block": 0, "target_controled": false, "tangrams_order": [[2, 5, 1, 8, 4, 7, 6, 3, 0, 9], [9, 1, 8, 3, 6, 7, 4, 2, 0, 5]], "roles": ["listener", "speaker"], "chat_mode": "single-utterance-unidirectional"}, {"images": [{"path": "page4-215.svg"}, {"path": "page6-160.svg"}, {"path": "page8-21.svg"}, {"path": "page6-172.svg"}, {"path": "page4-214.svg"}, {"path": "page7-245.svg"}, {"path": "page6-121.svg"}, {"path": "page6-149.svg"}, {"path": "page8-215.svg"}, {"path": "page4-11.svg"}], "target": "page4-214.svg", "target_snd_class": "high", "block": 0, "target_controled": false, "tangrams_order": [[9, 1, 8, 3, 6, 7, 4, 2, 0, 5], [2, 5, 1, 8, 4, 7, 6, 3, 0, 9]], "roles": ["speaker", "listener"], "chat_mode": "single-utterance-unidirectional"}, {"images": [{"path": "page4-215.svg"}, {"path": "page6-160.svg"}, {"path": "page8-21.svg"}, {"path": "page6-172.svg"}, {"path": "page4-214.svg"}, {"path": "page7-245.svg"}, {"path": "page6-121.svg"}, {"path": "page6-149.svg"}, {"path": "page8-215.svg"}, {"path": "page4-11.svg"}], "target": "page7-245.svg", "target_snd_class": "high", "block": 0, "target_controled": false, "tangrams_order": [[2, 5, 1, 8, 4, 7, 6, 3, 0, 9], [9, 1, 8, 3, 6, 7, 4, 2, 0, 5]], "roles": ["listener", "speaker"], "chat_mode": "single-utterance-unidirectional"}, {"images": [{"path": "page4-215.svg"}, {"path": "page6-160.svg"}, {"path": "page8-21.svg"}, {"path": "page6-172.svg"}, {"path": "page4-214.svg"}, {"path": "page7-245.svg"}, {"path": "page6-121.svg"}, {"path": "page6-149.svg"}, {"path": "page8-215.svg"}, {"path": "page4-11.svg"}], "target": "page6-121.svg", "target_snd_class": "high", "block": 0, "target_controled": false, "tangrams_order": [[9, 1, 8, 3, 6, 7, 4, 2, 0, 5], [2, 5, 1, 8, 4, 7, 6, 3, 0, 9]], "roles": ["speaker", "listener"], "chat_mode": "single-utterance-unidirectional"}, {"images": [{"path": "page4-215.svg"}, {"path": "page6-160.svg"}, {"path": "page8-21.svg"}, {"path": "page6-172.svg"}, {"path": "page4-214.svg"}, {"path": "page7-245.svg"}, {"path": "page6-121.svg"}, {"path": "page6-149.svg"}, {"path": "page8-215.svg"}, {"path": "page4-11.svg"}], "target": "page6-149.svg", "target_snd_class": "high", "block": 0, "target_controled": false, "tangrams_order": [[2, 5, 1, 8, 4, 7, 6, 3, 0, 9], [9, 1, 8, 3, 6, 7, 4, 2, 0, 5]], "roles": ["listener", "speaker"], "chat_mode": "single-utterance-unidirectional"}, {"images": [{"path": "page4-215.svg"}, {"path": "page6-160.svg"}, {"path": "page8-21.svg"}, {"path": "page6-172.svg"}, {"path": "page4-214.svg"}, {"path": "page7-245.svg"}, {"path": "page6-121.svg"}, {"path": "page6-149.svg"}, {"path": "page8-215.svg"}, {"path": "page4-11.svg"}], "target": "page8-215.svg", "target_snd_class": "low", "block": 0, "target_controled": false, "tangrams_order": [[9, 1, 8, 3, 6, 7, 4, 2, 0, 5], [2, 5, 1, 8, 4, 7, 6, 3, 0, 9]], "roles": ["speaker", "listener"], "chat_mode": "single-utterance-unidirectional"}, {"images": [{"path": "page4-215.svg"}, {"path": "page6-160.svg"}, {"path": "page8-21.svg"}, {"path": "page6-172.svg"}, {"path": "page4-214.svg"}, {"path": "page7-245.svg"}, {"path": "page6-121.svg"}, {"path": "page6-149.svg"}, {"path": "page8-215.svg"}, {"path": "page4-11.svg"}], "target": "page4-11.svg", "target_snd_class": "low", "block": 0, "target_controled": false, "tangrams_order": [[2, 5, 1, 8, 4, 7, 6, 3, 0, 9], [9, 1, 8, 3, 6, 7, 4, 2, 0, 5]], "roles": ["listener", "speaker"], "chat_mode": "single-utterance-unidirectional"}]}