{"comment": "phase2: 1 contexts, each context is 30 trials", "trials": [{"context": ["page6-160.svg", "page6-107.svg", "page7-157.svg", "page5-165.svg", "page2-36.svg", "page2-114.svg", "page2-133.svg", "page1-34.svg", "page3-70.svg", "page6-166.svg"], "target": "page1-34.svg", "target_snd_class": "high", "roles": ["speaker", "listener"], "tangrams_order": [[7, 4, 0, 6, 2, 9, 8, 1, 5, 3], [4, 0, 5, 1, 9, 8, 3, 6, 2, 7]], "block": 0, "controled": false, "images": [{"path": "page6-160.svg"}, {"path": "page6-107.svg"}, {"path": "page7-157.svg"}, {"path": "page5-165.svg"}, {"path": "page2-36.svg"}, {"path": "page2-114.svg"}, {"path": "page2-133.svg"}, {"path": "page1-34.svg"}, {"path": "page3-70.svg"}, {"path": "page6-166.svg"}], "chat_mode": "single-utterance-unidirectional"}, {"context": ["page6-160.svg", "page6-107.svg", "page7-157.svg", "page5-165.svg", "page2-36.svg", "page2-114.svg", "page2-133.svg", "page1-34.svg", "page3-70.svg", "page6-166.svg"], "target": "page5-165.svg", "target_snd_class": "low", "roles": ["speaker", "listener"], "tangrams_order": [[7, 4, 0, 6, 2, 9, 8, 1, 5, 3], [4, 0, 5, 1, 9, 8, 3, 6, 2, 7]], "block": 0, "controled": false, "images": [{"path": "page6-160.svg"}, {"path": "page6-107.svg"}, {"path": "page7-157.svg"}, {"path": "page5-165.svg"}, {"path": "page2-36.svg"}, {"path": "page2-114.svg"}, {"path": "page2-133.svg"}, {"path": "page1-34.svg"}, {"path": "page3-70.svg"}, {"path": "page6-166.svg"}], "chat_mode": "single-utterance-unidirectional"}, {"context": ["page6-160.svg", "page6-107.svg", "page7-157.svg", "page5-165.svg", "page2-36.svg", "page2-114.svg", "page2-133.svg", "page1-34.svg", "page3-70.svg", "page6-166.svg"], "target": "page3-70.svg", "target_snd_class": null, "roles": ["listener", "speaker"], "tangrams_order": [[4, 0, 5, 1, 9, 8, 3, 6, 2, 7], [7, 4, 0, 6, 2, 9, 8, 1, 5, 3]], "block": 0, "controled": true, "images": [{"path": "page6-160.svg"}, {"path": "page6-107.svg"}, {"path": "page7-157.svg"}, {"path": "page5-165.svg"}, {"path": "page2-36.svg"}, {"path": "page2-114.svg"}, {"path": "page2-133.svg"}, {"path": "page1-34.svg"}, {"path": "page3-70.svg"}, {"path": "page6-166.svg"}], "chat_mode": "single-utterance-unidirectional"}, {"context": ["page6-160.svg", "page6-107.svg", "page7-157.svg", "page5-165.svg", "page2-36.svg", "page2-114.svg", "page2-133.svg", "page1-34.svg", "page3-70.svg", "page6-166.svg"], "target": "page6-107.svg", "target_snd_class": "low", "roles": ["speaker", "listener"], "tangrams_order": [[7, 4, 0, 6, 2, 9, 8, 1, 5, 3], [4, 0, 5, 1, 9, 8, 3, 6, 2, 7]], "block": 0, "controled": false, "images": [{"path": "page6-160.svg"}, {"path": "page6-107.svg"}, {"path": "page7-157.svg"}, {"path": "page5-165.svg"}, {"path": "page2-36.svg"}, {"path": "page2-114.svg"}, {"path": "page2-133.svg"}, {"path": "page1-34.svg"}, {"path": "page3-70.svg"}, {"path": "page6-166.svg"}], "chat_mode": "single-utterance-unidirectional"}, {"context": ["page6-160.svg", "page6-107.svg", "page7-157.svg", "page5-165.svg", "page2-36.svg", "page2-114.svg", "page2-133.svg", "page1-34.svg", "page3-70.svg", "page6-166.svg"], "target": "page6-166.svg", "target_snd_class": "high", "roles": ["speaker", "listener"], "tangrams_order": [[7, 4, 0, 6, 2, 9, 8, 1, 5, 3], [4, 0, 5, 1, 9, 8, 3, 6, 2, 7]], "block": 0, "controled": false, "images": [{"path": "page6-160.svg"}, {"path": "page6-107.svg"}, {"path": "page7-157.svg"}, {"path": "page5-165.svg"}, {"path": "page2-36.svg"}, {"path": "page2-114.svg"}, {"path": "page2-133.svg"}, {"path": "page1-34.svg"}, {"path": "page3-70.svg"}, {"path": "page6-166.svg"}], "chat_mode": "single-utterance-unidirectional"}, {"context": ["page6-160.svg", "page6-107.svg", "page7-157.svg", "page5-165.svg", "page2-36.svg", "page2-114.svg", "page2-133.svg", "page1-34.svg", "page3-70.svg", "page6-166.svg"], "target": "page6-160.svg", "target_snd_class": "low", "roles": ["speaker", "listener"], "tangrams_order": [[7, 4, 0, 6, 2, 9, 8, 1, 5, 3], [4, 0, 5, 1, 9, 8, 3, 6, 2, 7]], "block": 0, "controled": false, "images": [{"path": "page6-160.svg"}, {"path": "page6-107.svg"}, {"path": "page7-157.svg"}, {"path": "page5-165.svg"}, {"path": "page2-36.svg"}, {"path": "page2-114.svg"}, {"path": "page2-133.svg"}, {"path": "page1-34.svg"}, {"path": "page3-70.svg"}, {"path": "page6-166.svg"}], "chat_mode": "single-utterance-unidirectional"}, {"context": ["page6-160.svg", "page6-107.svg", "page7-157.svg", "page5-165.svg", "page2-36.svg", "page2-114.svg", "page2-133.svg", "page1-34.svg", "page3-70.svg", "page6-166.svg"], "target": "page1-34.svg", "target_snd_class": "high", "roles": ["listener", "speaker"], "tangrams_order": [[4, 0, 5, 1, 9, 8, 3, 6, 2, 7], [7, 4, 0, 6, 2, 9, 8, 1, 5, 3]], "block": 1, "controled": false, "images": [{"path": "page6-160.svg"}, {"path": "page6-107.svg"}, {"path": "page7-157.svg"}, {"path": "page5-165.svg"}, {"path": "page2-36.svg"}, {"path": "page2-114.svg"}, {"path": "page2-133.svg"}, {"path": "page1-34.svg"}, {"path": "page3-70.svg"}, {"path": "page6-166.svg"}], "chat_mode": "single-utterance-unidirectional"}, {"context": ["page6-160.svg", "page6-107.svg", "page7-157.svg", "page5-165.svg", "page2-36.svg", "page2-114.svg", "page2-133.svg", "page1-34.svg", "page3-70.svg", "page6-166.svg"], "target": "page2-114.svg", "target_snd_class": null, "roles": ["listener", "speaker"], "tangrams_order": [[4, 0, 5, 1, 9, 8, 3, 6, 2, 7], [7, 4, 0, 6, 2, 9, 8, 1, 5, 3]], "block": 1, "controled": true, "images": [{"path": "page6-160.svg"}, {"path": "page6-107.svg"}, {"path": "page7-157.svg"}, {"path": "page5-165.svg"}, {"path": "page2-36.svg"}, {"path": "page2-114.svg"}, {"path": "page2-133.svg"}, {"path": "page1-34.svg"}, {"path": "page3-70.svg"}, {"path": "page6-166.svg"}], "chat_mode": "single-utterance-unidirectional"}, {"context": ["page6-160.svg", "page6-107.svg", "page7-157.svg", "page5-165.svg", "page2-36.svg", "page2-114.svg", "page2-133.svg", "page1-34.svg", "page3-70.svg", "page6-166.svg"], "target": "page6-107.svg", "target_snd_class": "low", "roles": ["listener", "speaker"], "tangrams_order": [[4, 0, 5, 1, 9, 8, 3, 6, 2, 7], [7, 4, 0, 6, 2, 9, 8, 1, 5, 3]], "block": 1, "controled": false, "images": [{"path": "page6-160.svg"}, {"path": "page6-107.svg"}, {"path": "page7-157.svg"}, {"path": "page5-165.svg"}, {"path": "page2-36.svg"}, {"path": "page2-114.svg"}, {"path": "page2-133.svg"}, {"path": "page1-34.svg"}, {"path": "page3-70.svg"}, {"path": "page6-166.svg"}], "chat_mode": "single-utterance-unidirectional"}, {"context": ["page6-160.svg", "page6-107.svg", "page7-157.svg", "page5-165.svg", "page2-36.svg", "page2-114.svg", "page2-133.svg", "page1-34.svg", "page3-70.svg", "page6-166.svg"], "target": "page5-165.svg", "target_snd_class": "low", "roles": ["listener", "speaker"], "tangrams_order": [[4, 0, 5, 1, 9, 8, 3, 6, 2, 7], [7, 4, 0, 6, 2, 9, 8, 1, 5, 3]], "block": 1, "controled": false, "images": [{"path": "page6-160.svg"}, {"path": "page6-107.svg"}, {"path": "page7-157.svg"}, {"path": "page5-165.svg"}, {"path": "page2-36.svg"}, {"path": "page2-114.svg"}, {"path": "page2-133.svg"}, {"path": "page1-34.svg"}, {"path": "page3-70.svg"}, {"path": "page6-166.svg"}], "chat_mode": "single-utterance-unidirectional"}, {"context": ["page6-160.svg", "page6-107.svg", "page7-157.svg", "page5-165.svg", "page2-36.svg", "page2-114.svg", "page2-133.svg", "page1-34.svg", "page3-70.svg", "page6-166.svg"], "target": "page6-160.svg", "target_snd_class": "low", "roles": ["listener", "speaker"], "tangrams_order": [[4, 0, 5, 1, 9, 8, 3, 6, 2, 7], [7, 4, 0, 6, 2, 9, 8, 1, 5, 3]], "block": 1, "controled": false, "images": [{"path": "page6-160.svg"}, {"path": "page6-107.svg"}, {"path": "page7-157.svg"}, {"path": "page5-165.svg"}, {"path": "page2-36.svg"}, {"path": "page2-114.svg"}, {"path": "page2-133.svg"}, {"path": "page1-34.svg"}, {"path": "page3-70.svg"}, {"path": "page6-166.svg"}], "chat_mode": "single-utterance-unidirectional"}, {"context": ["page6-160.svg", "page6-107.svg", "page7-157.svg", "page5-165.svg", "page2-36.svg", "page2-114.svg", "page2-133.svg", "page1-34.svg", "page3-70.svg", "page6-166.svg"], "target": "page6-166.svg", "target_snd_class": "high", "roles": ["listener", "speaker"], "tangrams_order": [[4, 0, 5, 1, 9, 8, 3, 6, 2, 7], [7, 4, 0, 6, 2, 9, 8, 1, 5, 3]], "block": 1, "controled": false, "images": [{"path": "page6-160.svg"}, {"path": "page6-107.svg"}, {"path": "page7-157.svg"}, {"path": "page5-165.svg"}, {"path": "page2-36.svg"}, {"path": "page2-114.svg"}, {"path": "page2-133.svg"}, {"path": "page1-34.svg"}, {"path": "page3-70.svg"}, {"path": "page6-166.svg"}], "chat_mode": "single-utterance-unidirectional"}, {"context": ["page6-160.svg", "page6-107.svg", "page7-157.svg", "page5-165.svg", "page2-36.svg", "page2-114.svg", "page2-133.svg", "page1-34.svg", "page3-70.svg", "page6-166.svg"], "target": "page2-133.svg", "target_snd_class": null, "roles": ["listener", "speaker"], "tangrams_order": [[4, 0, 5, 1, 9, 8, 3, 6, 2, 7], [7, 4, 0, 6, 2, 9, 8, 1, 5, 3]], "block": 2, "controled": true, "images": [{"path": "page6-160.svg"}, {"path": "page6-107.svg"}, {"path": "page7-157.svg"}, {"path": "page5-165.svg"}, {"path": "page2-36.svg"}, {"path": "page2-114.svg"}, {"path": "page2-133.svg"}, {"path": "page1-34.svg"}, {"path": "page3-70.svg"}, {"path": "page6-166.svg"}], "chat_mode": "single-utterance-unidirectional"}, {"context": ["page6-160.svg", "page6-107.svg", "page7-157.svg", "page5-165.svg", "page2-36.svg", "page2-114.svg", "page2-133.svg", "page1-34.svg", "page3-70.svg", "page6-166.svg"], "target": "page5-165.svg", "target_snd_class": "low", "roles": ["speaker", "listener"], "tangrams_order": [[7, 4, 0, 6, 2, 9, 8, 1, 5, 3], [4, 0, 5, 1, 9, 8, 3, 6, 2, 7]], "block": 2, "controled": false, "images": [{"path": "page6-160.svg"}, {"path": "page6-107.svg"}, {"path": "page7-157.svg"}, {"path": "page5-165.svg"}, {"path": "page2-36.svg"}, {"path": "page2-114.svg"}, {"path": "page2-133.svg"}, {"path": "page1-34.svg"}, {"path": "page3-70.svg"}, {"path": "page6-166.svg"}], "chat_mode": "single-utterance-unidirectional"}, {"context": ["page6-160.svg", "page6-107.svg", "page7-157.svg", "page5-165.svg", "page2-36.svg", "page2-114.svg", "page2-133.svg", "page1-34.svg", "page3-70.svg", "page6-166.svg"], "target": "page6-166.svg", "target_snd_class": "high", "roles": ["speaker", "listener"], "tangrams_order": [[7, 4, 0, 6, 2, 9, 8, 1, 5, 3], [4, 0, 5, 1, 9, 8, 3, 6, 2, 7]], "block": 2, "controled": false, "images": [{"path": "page6-160.svg"}, {"path": "page6-107.svg"}, {"path": "page7-157.svg"}, {"path": "page5-165.svg"}, {"path": "page2-36.svg"}, {"path": "page2-114.svg"}, {"path": "page2-133.svg"}, {"path": "page1-34.svg"}, {"path": "page3-70.svg"}, {"path": "page6-166.svg"}], "chat_mode": "single-utterance-unidirectional"}, {"context": ["page6-160.svg", "page6-107.svg", "page7-157.svg", "page5-165.svg", "page2-36.svg", "page2-114.svg", "page2-133.svg", "page1-34.svg", "page3-70.svg", "page6-166.svg"], "target": "page6-107.svg", "target_snd_class": "low", "roles": ["speaker", "listener"], "tangrams_order": [[7, 4, 0, 6, 2, 9, 8, 1, 5, 3], [4, 0, 5, 1, 9, 8, 3, 6, 2, 7]], "block": 2, "controled": false, "images": [{"path": "page6-160.svg"}, {"path": "page6-107.svg"}, {"path": "page7-157.svg"}, {"path": "page5-165.svg"}, {"path": "page2-36.svg"}, {"path": "page2-114.svg"}, {"path": "page2-133.svg"}, {"path": "page1-34.svg"}, {"path": "page3-70.svg"}, {"path": "page6-166.svg"}], "chat_mode": "single-utterance-unidirectional"}, {"context": ["page6-160.svg", "page6-107.svg", "page7-157.svg", "page5-165.svg", "page2-36.svg", "page2-114.svg", "page2-133.svg", "page1-34.svg", "page3-70.svg", "page6-166.svg"], "target": "page6-160.svg", "target_snd_class": "low", "roles": ["speaker", "listener"], "tangrams_order": [[7, 4, 0, 6, 2, 9, 8, 1, 5, 3], [4, 0, 5, 1, 9, 8, 3, 6, 2, 7]], "block": 2, "controled": false, "images": [{"path": "page6-160.svg"}, {"path": "page6-107.svg"}, {"path": "page7-157.svg"}, {"path": "page5-165.svg"}, {"path": "page2-36.svg"}, {"path": "page2-114.svg"}, {"path": "page2-133.svg"}, {"path": "page1-34.svg"}, {"path": "page3-70.svg"}, {"path": "page6-166.svg"}], "chat_mode": "single-utterance-unidirectional"}, {"context": ["page6-160.svg", "page6-107.svg", "page7-157.svg", "page5-165.svg", "page2-36.svg", "page2-114.svg", "page2-133.svg", "page1-34.svg", "page3-70.svg", "page6-166.svg"], "target": "page1-34.svg", "target_snd_class": "high", "roles": ["speaker", "listener"], "tangrams_order": [[7, 4, 0, 6, 2, 9, 8, 1, 5, 3], [4, 0, 5, 1, 9, 8, 3, 6, 2, 7]], "block": 2, "controled": false, "images": [{"path": "page6-160.svg"}, {"path": "page6-107.svg"}, {"path": "page7-157.svg"}, {"path": "page5-165.svg"}, {"path": "page2-36.svg"}, {"path": "page2-114.svg"}, {"path": "page2-133.svg"}, {"path": "page1-34.svg"}, {"path": "page3-70.svg"}, {"path": "page6-166.svg"}], "chat_mode": "single-utterance-unidirectional"}, {"context": ["page6-160.svg", "page6-107.svg", "page7-157.svg", "page5-165.svg", "page2-36.svg", "page2-114.svg", "page2-133.svg", "page1-34.svg", "page3-70.svg", "page6-166.svg"], "target": "page6-160.svg", "target_snd_class": "low", "roles": ["listener", "speaker"], "tangrams_order": [[4, 0, 5, 1, 9, 8, 3, 6, 2, 7], [7, 4, 0, 6, 2, 9, 8, 1, 5, 3]], "block": 3, "controled": false, "images": [{"path": "page6-160.svg"}, {"path": "page6-107.svg"}, {"path": "page7-157.svg"}, {"path": "page5-165.svg"}, {"path": "page2-36.svg"}, {"path": "page2-114.svg"}, {"path": "page2-133.svg"}, {"path": "page1-34.svg"}, {"path": "page3-70.svg"}, {"path": "page6-166.svg"}], "chat_mode": "single-utterance-unidirectional"}, {"context": ["page6-160.svg", "page6-107.svg", "page7-157.svg", "page5-165.svg", "page2-36.svg", "page2-114.svg", "page2-133.svg", "page1-34.svg", "page3-70.svg", "page6-166.svg"], "target": "page5-165.svg", "target_snd_class": "low", "roles": ["listener", "speaker"], "tangrams_order": [[4, 0, 5, 1, 9, 8, 3, 6, 2, 7], [7, 4, 0, 6, 2, 9, 8, 1, 5, 3]], "block": 3, "controled": false, "images": [{"path": "page6-160.svg"}, {"path": "page6-107.svg"}, {"path": "page7-157.svg"}, {"path": "page5-165.svg"}, {"path": "page2-36.svg"}, {"path": "page2-114.svg"}, {"path": "page2-133.svg"}, {"path": "page1-34.svg"}, {"path": "page3-70.svg"}, {"path": "page6-166.svg"}], "chat_mode": "single-utterance-unidirectional"}, {"context": ["page6-160.svg", "page6-107.svg", "page7-157.svg", "page5-165.svg", "page2-36.svg", "page2-114.svg", "page2-133.svg", "page1-34.svg", "page3-70.svg", "page6-166.svg"], "target": "page2-36.svg", "target_snd_class": null, "roles": ["listener", "speaker"], "tangrams_order": [[4, 0, 5, 1, 9, 8, 3, 6, 2, 7], [7, 4, 0, 6, 2, 9, 8, 1, 5, 3]], "block": 3, "controled": true, "images": [{"path": "page6-160.svg"}, {"path": "page6-107.svg"}, {"path": "page7-157.svg"}, {"path": "page5-165.svg"}, {"path": "page2-36.svg"}, {"path": "page2-114.svg"}, {"path": "page2-133.svg"}, {"path": "page1-34.svg"}, {"path": "page3-70.svg"}, {"path": "page6-166.svg"}], "chat_mode": "single-utterance-unidirectional"}, {"context": ["page6-160.svg", "page6-107.svg", "page7-157.svg", "page5-165.svg", "page2-36.svg", "page2-114.svg", "page2-133.svg", "page1-34.svg", "page3-70.svg", "page6-166.svg"], "target": "page6-107.svg", "target_snd_class": "low", "roles": ["listener", "speaker"], "tangrams_order": [[4, 0, 5, 1, 9, 8, 3, 6, 2, 7], [7, 4, 0, 6, 2, 9, 8, 1, 5, 3]], "block": 3, "controled": false, "images": [{"path": "page6-160.svg"}, {"path": "page6-107.svg"}, {"path": "page7-157.svg"}, {"path": "page5-165.svg"}, {"path": "page2-36.svg"}, {"path": "page2-114.svg"}, {"path": "page2-133.svg"}, {"path": "page1-34.svg"}, {"path": "page3-70.svg"}, {"path": "page6-166.svg"}], "chat_mode": "single-utterance-unidirectional"}, {"context": ["page6-160.svg", "page6-107.svg", "page7-157.svg", "page5-165.svg", "page2-36.svg", "page2-114.svg", "page2-133.svg", "page1-34.svg", "page3-70.svg", "page6-166.svg"], "target": "page1-34.svg", "target_snd_class": "high", "roles": ["listener", "speaker"], "tangrams_order": [[4, 0, 5, 1, 9, 8, 3, 6, 2, 7], [7, 4, 0, 6, 2, 9, 8, 1, 5, 3]], "block": 3, "controled": false, "images": [{"path": "page6-160.svg"}, {"path": "page6-107.svg"}, {"path": "page7-157.svg"}, {"path": "page5-165.svg"}, {"path": "page2-36.svg"}, {"path": "page2-114.svg"}, {"path": "page2-133.svg"}, {"path": "page1-34.svg"}, {"path": "page3-70.svg"}, {"path": "page6-166.svg"}], "chat_mode": "single-utterance-unidirectional"}, {"context": ["page6-160.svg", "page6-107.svg", "page7-157.svg", "page5-165.svg", "page2-36.svg", "page2-114.svg", "page2-133.svg", "page1-34.svg", "page3-70.svg", "page6-166.svg"], "target": "page6-166.svg", "target_snd_class": "high", "roles": ["listener", "speaker"], "tangrams_order": [[4, 0, 5, 1, 9, 8, 3, 6, 2, 7], [7, 4, 0, 6, 2, 9, 8, 1, 5, 3]], "block": 3, "controled": false, "images": [{"path": "page6-160.svg"}, {"path": "page6-107.svg"}, {"path": "page7-157.svg"}, {"path": "page5-165.svg"}, {"path": "page2-36.svg"}, {"path": "page2-114.svg"}, {"path": "page2-133.svg"}, {"path": "page1-34.svg"}, {"path": "page3-70.svg"}, {"path": "page6-166.svg"}], "chat_mode": "single-utterance-unidirectional"}, {"context": ["page6-160.svg", "page6-107.svg", "page7-157.svg", "page5-165.svg", "page2-36.svg", "page2-114.svg", "page2-133.svg", "page1-34.svg", "page3-70.svg", "page6-166.svg"], "target": "page1-34.svg", "target_snd_class": "high", "roles": ["speaker", "listener"], "tangrams_order": [[7, 4, 0, 6, 2, 9, 8, 1, 5, 3], [4, 0, 5, 1, 9, 8, 3, 6, 2, 7]], "block": 4, "controled": false, "images": [{"path": "page6-160.svg"}, {"path": "page6-107.svg"}, {"path": "page7-157.svg"}, {"path": "page5-165.svg"}, {"path": "page2-36.svg"}, {"path": "page2-114.svg"}, {"path": "page2-133.svg"}, {"path": "page1-34.svg"}, {"path": "page3-70.svg"}, {"path": "page6-166.svg"}], "chat_mode": "single-utterance-unidirectional"}, {"context": ["page6-160.svg", "page6-107.svg", "page7-157.svg", "page5-165.svg", "page2-36.svg", "page2-114.svg", "page2-133.svg", "page1-34.svg", "page3-70.svg", "page6-166.svg"], "target": "page6-107.svg", "target_snd_class": "low", "roles": ["speaker", "listener"], "tangrams_order": [[7, 4, 0, 6, 2, 9, 8, 1, 5, 3], [4, 0, 5, 1, 9, 8, 3, 6, 2, 7]], "block": 4, "controled": false, "images": [{"path": "page6-160.svg"}, {"path": "page6-107.svg"}, {"path": "page7-157.svg"}, {"path": "page5-165.svg"}, {"path": "page2-36.svg"}, {"path": "page2-114.svg"}, {"path": "page2-133.svg"}, {"path": "page1-34.svg"}, {"path": "page3-70.svg"}, {"path": "page6-166.svg"}], "chat_mode": "single-utterance-unidirectional"}, {"context": ["page6-160.svg", "page6-107.svg", "page7-157.svg", "page5-165.svg", "page2-36.svg", "page2-114.svg", "page2-133.svg", "page1-34.svg", "page3-70.svg", "page6-166.svg"], "target": "page5-165.svg", "target_snd_class": "low", "roles": ["speaker", "listener"], "tangrams_order": [[7, 4, 0, 6, 2, 9, 8, 1, 5, 3], [4, 0, 5, 1, 9, 8, 3, 6, 2, 7]], "block": 4, "controled": false, "images": [{"path": "page6-160.svg"}, {"path": "page6-107.svg"}, {"path": "page7-157.svg"}, {"path": "page5-165.svg"}, {"path": "page2-36.svg"}, {"path": "page2-114.svg"}, {"path": "page2-133.svg"}, {"path": "page1-34.svg"}, {"path": "page3-70.svg"}, {"path": "page6-166.svg"}], "chat_mode": "single-utterance-unidirectional"}, {"context": ["page6-160.svg", "page6-107.svg", "page7-157.svg", "page5-165.svg", "page2-36.svg", "page2-114.svg", "page2-133.svg", "page1-34.svg", "page3-70.svg", "page6-166.svg"], "target": "page6-166.svg", "target_snd_class": "high", "roles": ["speaker", "listener"], "tangrams_order": [[7, 4, 0, 6, 2, 9, 8, 1, 5, 3], [4, 0, 5, 1, 9, 8, 3, 6, 2, 7]], "block": 4, "controled": false, "images": [{"path": "page6-160.svg"}, {"path": "page6-107.svg"}, {"path": "page7-157.svg"}, {"path": "page5-165.svg"}, {"path": "page2-36.svg"}, {"path": "page2-114.svg"}, {"path": "page2-133.svg"}, {"path": "page1-34.svg"}, {"path": "page3-70.svg"}, {"path": "page6-166.svg"}], "chat_mode": "single-utterance-unidirectional"}, {"context": ["page6-160.svg", "page6-107.svg", "page7-157.svg", "page5-165.svg", "page2-36.svg", "page2-114.svg", "page2-133.svg", "page1-34.svg", "page3-70.svg", "page6-166.svg"], "target": "page7-157.svg", "target_snd_class": null, "roles": ["listener", "speaker"], "tangrams_order": [[4, 0, 5, 1, 9, 8, 3, 6, 2, 7], [7, 4, 0, 6, 2, 9, 8, 1, 5, 3]], "block": 4, "controled": true, "images": [{"path": "page6-160.svg"}, {"path": "page6-107.svg"}, {"path": "page7-157.svg"}, {"path": "page5-165.svg"}, {"path": "page2-36.svg"}, {"path": "page2-114.svg"}, {"path": "page2-133.svg"}, {"path": "page1-34.svg"}, {"path": "page3-70.svg"}, {"path": "page6-166.svg"}], "chat_mode": "single-utterance-unidirectional"}, {"context": ["page6-160.svg", "page6-107.svg", "page7-157.svg", "page5-165.svg", "page2-36.svg", "page2-114.svg", "page2-133.svg", "page1-34.svg", "page3-70.svg", "page6-166.svg"], "target": "page6-160.svg", "target_snd_class": "low", "roles": ["speaker", "listener"], "tangrams_order": [[7, 4, 0, 6, 2, 9, 8, 1, 5, 3], [4, 0, 5, 1, 9, 8, 3, 6, 2, 7]], "block": 4, "controled": false, "images": [{"path": "page6-160.svg"}, {"path": "page6-107.svg"}, {"path": "page7-157.svg"}, {"path": "page5-165.svg"}, {"path": "page2-36.svg"}, {"path": "page2-114.svg"}, {"path": "page2-133.svg"}, {"path": "page1-34.svg"}, {"path": "page3-70.svg"}, {"path": "page6-166.svg"}], "chat_mode": "single-utterance-unidirectional"}]}