{"comment": "phase2: 1 contexts, each context is 30 trials", "trials": [{"context": ["page6-185.svg", "page1-172.svg", "page5-26.svg", "page2-190.svg", "page7-15.svg", "page1-128.svg", "page6-166.svg", "page6-228.svg", "page2-114.svg", "page6-167.svg"], "target": "page7-15.svg", "target_snd_class": "low", "roles": ["speaker", "listener"], "tangrams_order": [[3, 7, 8, 6, 0, 4, 9, 5, 2, 1], [2, 9, 7, 8, 6, 3, 0, 4, 5, 1]], "block": 0, "controled": false, "images": [{"path": "page6-185.svg"}, {"path": "page1-172.svg"}, {"path": "page5-26.svg"}, {"path": "page2-190.svg"}, {"path": "page7-15.svg"}, {"path": "page1-128.svg"}, {"path": "page6-166.svg"}, {"path": "page6-228.svg"}, {"path": "page2-114.svg"}, {"path": "page6-167.svg"}], "chat_mode": "single-utterance-unidirectional"}, {"context": ["page6-185.svg", "page1-172.svg", "page5-26.svg", "page2-190.svg", "page7-15.svg", "page1-128.svg", "page6-166.svg", "page6-228.svg", "page2-114.svg", "page6-167.svg"], "target": "page5-26.svg", "target_snd_class": "low", "roles": ["speaker", "listener"], "tangrams_order": [[3, 7, 8, 6, 0, 4, 9, 5, 2, 1], [2, 9, 7, 8, 6, 3, 0, 4, 5, 1]], "block": 0, "controled": false, "images": [{"path": "page6-185.svg"}, {"path": "page1-172.svg"}, {"path": "page5-26.svg"}, {"path": "page2-190.svg"}, {"path": "page7-15.svg"}, {"path": "page1-128.svg"}, {"path": "page6-166.svg"}, {"path": "page6-228.svg"}, {"path": "page2-114.svg"}, {"path": "page6-167.svg"}], "chat_mode": "single-utterance-unidirectional"}, {"context": ["page6-185.svg", "page1-172.svg", "page5-26.svg", "page2-190.svg", "page7-15.svg", "page1-128.svg", "page6-166.svg", "page6-228.svg", "page2-114.svg", "page6-167.svg"], "target": "page1-128.svg", "target_snd_class": null, "roles": ["listener", "speaker"], "tangrams_order": [[2, 9, 7, 8, 6, 3, 0, 4, 5, 1], [3, 7, 8, 6, 0, 4, 9, 5, 2, 1]], "block": 0, "controled": true, "images": [{"path": "page6-185.svg"}, {"path": "page1-172.svg"}, {"path": "page5-26.svg"}, {"path": "page2-190.svg"}, {"path": "page7-15.svg"}, {"path": "page1-128.svg"}, {"path": "page6-166.svg"}, {"path": "page6-228.svg"}, {"path": "page2-114.svg"}, {"path": "page6-167.svg"}], "chat_mode": "single-utterance-unidirectional"}, {"context": ["page6-185.svg", "page1-172.svg", "page5-26.svg", "page2-190.svg", "page7-15.svg", "page1-128.svg", "page6-166.svg", "page6-228.svg", "page2-114.svg", "page6-167.svg"], "target": "page6-185.svg", "target_snd_class": "low", "roles": ["speaker", "listener"], "tangrams_order": [[3, 7, 8, 6, 0, 4, 9, 5, 2, 1], [2, 9, 7, 8, 6, 3, 0, 4, 5, 1]], "block": 0, "controled": false, "images": [{"path": "page6-185.svg"}, {"path": "page1-172.svg"}, {"path": "page5-26.svg"}, {"path": "page2-190.svg"}, {"path": "page7-15.svg"}, {"path": "page1-128.svg"}, {"path": "page6-166.svg"}, {"path": "page6-228.svg"}, {"path": "page2-114.svg"}, {"path": "page6-167.svg"}], "chat_mode": "single-utterance-unidirectional"}, {"context": ["page6-185.svg", "page1-172.svg", "page5-26.svg", "page2-190.svg", "page7-15.svg", "page1-128.svg", "page6-166.svg", "page6-228.svg", "page2-114.svg", "page6-167.svg"], "target": "page2-114.svg", "target_snd_class": "high", "roles": ["speaker", "listener"], "tangrams_order": [[3, 7, 8, 6, 0, 4, 9, 5, 2, 1], [2, 9, 7, 8, 6, 3, 0, 4, 5, 1]], "block": 0, "controled": false, "images": [{"path": "page6-185.svg"}, {"path": "page1-172.svg"}, {"path": "page5-26.svg"}, {"path": "page2-190.svg"}, {"path": "page7-15.svg"}, {"path": "page1-128.svg"}, {"path": "page6-166.svg"}, {"path": "page6-228.svg"}, {"path": "page2-114.svg"}, {"path": "page6-167.svg"}], "chat_mode": "single-utterance-unidirectional"}, {"context": ["page6-185.svg", "page1-172.svg", "page5-26.svg", "page2-190.svg", "page7-15.svg", "page1-128.svg", "page6-166.svg", "page6-228.svg", "page2-114.svg", "page6-167.svg"], "target": "page6-166.svg", "target_snd_class": "high", "roles": ["speaker", "listener"], "tangrams_order": [[3, 7, 8, 6, 0, 4, 9, 5, 2, 1], [2, 9, 7, 8, 6, 3, 0, 4, 5, 1]], "block": 0, "controled": false, "images": [{"path": "page6-185.svg"}, {"path": "page1-172.svg"}, {"path": "page5-26.svg"}, {"path": "page2-190.svg"}, {"path": "page7-15.svg"}, {"path": "page1-128.svg"}, {"path": "page6-166.svg"}, {"path": "page6-228.svg"}, {"path": "page2-114.svg"}, {"path": "page6-167.svg"}], "chat_mode": "single-utterance-unidirectional"}, {"context": ["page6-185.svg", "page1-172.svg", "page5-26.svg", "page2-190.svg", "page7-15.svg", "page1-128.svg", "page6-166.svg", "page6-228.svg", "page2-114.svg", "page6-167.svg"], "target": "page7-15.svg", "target_snd_class": "low", "roles": ["listener", "speaker"], "tangrams_order": [[2, 9, 7, 8, 6, 3, 0, 4, 5, 1], [3, 7, 8, 6, 0, 4, 9, 5, 2, 1]], "block": 1, "controled": false, "images": [{"path": "page6-185.svg"}, {"path": "page1-172.svg"}, {"path": "page5-26.svg"}, {"path": "page2-190.svg"}, {"path": "page7-15.svg"}, {"path": "page1-128.svg"}, {"path": "page6-166.svg"}, {"path": "page6-228.svg"}, {"path": "page2-114.svg"}, {"path": "page6-167.svg"}], "chat_mode": "single-utterance-unidirectional"}, {"context": ["page6-185.svg", "page1-172.svg", "page5-26.svg", "page2-190.svg", "page7-15.svg", "page1-128.svg", "page6-166.svg", "page6-228.svg", "page2-114.svg", "page6-167.svg"], "target": "page6-166.svg", "target_snd_class": "high", "roles": ["listener", "speaker"], "tangrams_order": [[2, 9, 7, 8, 6, 3, 0, 4, 5, 1], [3, 7, 8, 6, 0, 4, 9, 5, 2, 1]], "block": 1, "controled": false, "images": [{"path": "page6-185.svg"}, {"path": "page1-172.svg"}, {"path": "page5-26.svg"}, {"path": "page2-190.svg"}, {"path": "page7-15.svg"}, {"path": "page1-128.svg"}, {"path": "page6-166.svg"}, {"path": "page6-228.svg"}, {"path": "page2-114.svg"}, {"path": "page6-167.svg"}], "chat_mode": "single-utterance-unidirectional"}, {"context": ["page6-185.svg", "page1-172.svg", "page5-26.svg", "page2-190.svg", "page7-15.svg", "page1-128.svg", "page6-166.svg", "page6-228.svg", "page2-114.svg", "page6-167.svg"], "target": "page2-114.svg", "target_snd_class": "high", "roles": ["listener", "speaker"], "tangrams_order": [[2, 9, 7, 8, 6, 3, 0, 4, 5, 1], [3, 7, 8, 6, 0, 4, 9, 5, 2, 1]], "block": 1, "controled": false, "images": [{"path": "page6-185.svg"}, {"path": "page1-172.svg"}, {"path": "page5-26.svg"}, {"path": "page2-190.svg"}, {"path": "page7-15.svg"}, {"path": "page1-128.svg"}, {"path": "page6-166.svg"}, {"path": "page6-228.svg"}, {"path": "page2-114.svg"}, {"path": "page6-167.svg"}], "chat_mode": "single-utterance-unidirectional"}, {"context": ["page6-185.svg", "page1-172.svg", "page5-26.svg", "page2-190.svg", "page7-15.svg", "page1-128.svg", "page6-166.svg", "page6-228.svg", "page2-114.svg", "page6-167.svg"], "target": "page6-185.svg", "target_snd_class": "low", "roles": ["listener", "speaker"], "tangrams_order": [[2, 9, 7, 8, 6, 3, 0, 4, 5, 1], [3, 7, 8, 6, 0, 4, 9, 5, 2, 1]], "block": 1, "controled": false, "images": [{"path": "page6-185.svg"}, {"path": "page1-172.svg"}, {"path": "page5-26.svg"}, {"path": "page2-190.svg"}, {"path": "page7-15.svg"}, {"path": "page1-128.svg"}, {"path": "page6-166.svg"}, {"path": "page6-228.svg"}, {"path": "page2-114.svg"}, {"path": "page6-167.svg"}], "chat_mode": "single-utterance-unidirectional"}, {"context": ["page6-185.svg", "page1-172.svg", "page5-26.svg", "page2-190.svg", "page7-15.svg", "page1-128.svg", "page6-166.svg", "page6-228.svg", "page2-114.svg", "page6-167.svg"], "target": "page5-26.svg", "target_snd_class": "low", "roles": ["listener", "speaker"], "tangrams_order": [[2, 9, 7, 8, 6, 3, 0, 4, 5, 1], [3, 7, 8, 6, 0, 4, 9, 5, 2, 1]], "block": 1, "controled": false, "images": [{"path": "page6-185.svg"}, {"path": "page1-172.svg"}, {"path": "page5-26.svg"}, {"path": "page2-190.svg"}, {"path": "page7-15.svg"}, {"path": "page1-128.svg"}, {"path": "page6-166.svg"}, {"path": "page6-228.svg"}, {"path": "page2-114.svg"}, {"path": "page6-167.svg"}], "chat_mode": "single-utterance-unidirectional"}, {"context": ["page6-185.svg", "page1-172.svg", "page5-26.svg", "page2-190.svg", "page7-15.svg", "page1-128.svg", "page6-166.svg", "page6-228.svg", "page2-114.svg", "page6-167.svg"], "target": "page6-167.svg", "target_snd_class": null, "roles": ["listener", "speaker"], "tangrams_order": [[2, 9, 7, 8, 6, 3, 0, 4, 5, 1], [3, 7, 8, 6, 0, 4, 9, 5, 2, 1]], "block": 1, "controled": true, "images": [{"path": "page6-185.svg"}, {"path": "page1-172.svg"}, {"path": "page5-26.svg"}, {"path": "page2-190.svg"}, {"path": "page7-15.svg"}, {"path": "page1-128.svg"}, {"path": "page6-166.svg"}, {"path": "page6-228.svg"}, {"path": "page2-114.svg"}, {"path": "page6-167.svg"}], "chat_mode": "single-utterance-unidirectional"}, {"context": ["page6-185.svg", "page1-172.svg", "page5-26.svg", "page2-190.svg", "page7-15.svg", "page1-128.svg", "page6-166.svg", "page6-228.svg", "page2-114.svg", "page6-167.svg"], "target": "page1-172.svg", "target_snd_class": null, "roles": ["listener", "speaker"], "tangrams_order": [[2, 9, 7, 8, 6, 3, 0, 4, 5, 1], [3, 7, 8, 6, 0, 4, 9, 5, 2, 1]], "block": 2, "controled": true, "images": [{"path": "page6-185.svg"}, {"path": "page1-172.svg"}, {"path": "page5-26.svg"}, {"path": "page2-190.svg"}, {"path": "page7-15.svg"}, {"path": "page1-128.svg"}, {"path": "page6-166.svg"}, {"path": "page6-228.svg"}, {"path": "page2-114.svg"}, {"path": "page6-167.svg"}], "chat_mode": "single-utterance-unidirectional"}, {"context": ["page6-185.svg", "page1-172.svg", "page5-26.svg", "page2-190.svg", "page7-15.svg", "page1-128.svg", "page6-166.svg", "page6-228.svg", "page2-114.svg", "page6-167.svg"], "target": "page2-114.svg", "target_snd_class": "high", "roles": ["speaker", "listener"], "tangrams_order": [[3, 7, 8, 6, 0, 4, 9, 5, 2, 1], [2, 9, 7, 8, 6, 3, 0, 4, 5, 1]], "block": 2, "controled": false, "images": [{"path": "page6-185.svg"}, {"path": "page1-172.svg"}, {"path": "page5-26.svg"}, {"path": "page2-190.svg"}, {"path": "page7-15.svg"}, {"path": "page1-128.svg"}, {"path": "page6-166.svg"}, {"path": "page6-228.svg"}, {"path": "page2-114.svg"}, {"path": "page6-167.svg"}], "chat_mode": "single-utterance-unidirectional"}, {"context": ["page6-185.svg", "page1-172.svg", "page5-26.svg", "page2-190.svg", "page7-15.svg", "page1-128.svg", "page6-166.svg", "page6-228.svg", "page2-114.svg", "page6-167.svg"], "target": "page5-26.svg", "target_snd_class": "low", "roles": ["speaker", "listener"], "tangrams_order": [[3, 7, 8, 6, 0, 4, 9, 5, 2, 1], [2, 9, 7, 8, 6, 3, 0, 4, 5, 1]], "block": 2, "controled": false, "images": [{"path": "page6-185.svg"}, {"path": "page1-172.svg"}, {"path": "page5-26.svg"}, {"path": "page2-190.svg"}, {"path": "page7-15.svg"}, {"path": "page1-128.svg"}, {"path": "page6-166.svg"}, {"path": "page6-228.svg"}, {"path": "page2-114.svg"}, {"path": "page6-167.svg"}], "chat_mode": "single-utterance-unidirectional"}, {"context": ["page6-185.svg", "page1-172.svg", "page5-26.svg", "page2-190.svg", "page7-15.svg", "page1-128.svg", "page6-166.svg", "page6-228.svg", "page2-114.svg", "page6-167.svg"], "target": "page7-15.svg", "target_snd_class": "low", "roles": ["speaker", "listener"], "tangrams_order": [[3, 7, 8, 6, 0, 4, 9, 5, 2, 1], [2, 9, 7, 8, 6, 3, 0, 4, 5, 1]], "block": 2, "controled": false, "images": [{"path": "page6-185.svg"}, {"path": "page1-172.svg"}, {"path": "page5-26.svg"}, {"path": "page2-190.svg"}, {"path": "page7-15.svg"}, {"path": "page1-128.svg"}, {"path": "page6-166.svg"}, {"path": "page6-228.svg"}, {"path": "page2-114.svg"}, {"path": "page6-167.svg"}], "chat_mode": "single-utterance-unidirectional"}, {"context": ["page6-185.svg", "page1-172.svg", "page5-26.svg", "page2-190.svg", "page7-15.svg", "page1-128.svg", "page6-166.svg", "page6-228.svg", "page2-114.svg", "page6-167.svg"], "target": "page6-166.svg", "target_snd_class": "high", "roles": ["speaker", "listener"], "tangrams_order": [[3, 7, 8, 6, 0, 4, 9, 5, 2, 1], [2, 9, 7, 8, 6, 3, 0, 4, 5, 1]], "block": 2, "controled": false, "images": [{"path": "page6-185.svg"}, {"path": "page1-172.svg"}, {"path": "page5-26.svg"}, {"path": "page2-190.svg"}, {"path": "page7-15.svg"}, {"path": "page1-128.svg"}, {"path": "page6-166.svg"}, {"path": "page6-228.svg"}, {"path": "page2-114.svg"}, {"path": "page6-167.svg"}], "chat_mode": "single-utterance-unidirectional"}, {"context": ["page6-185.svg", "page1-172.svg", "page5-26.svg", "page2-190.svg", "page7-15.svg", "page1-128.svg", "page6-166.svg", "page6-228.svg", "page2-114.svg", "page6-167.svg"], "target": "page6-185.svg", "target_snd_class": "low", "roles": ["speaker", "listener"], "tangrams_order": [[3, 7, 8, 6, 0, 4, 9, 5, 2, 1], [2, 9, 7, 8, 6, 3, 0, 4, 5, 1]], "block": 2, "controled": false, "images": [{"path": "page6-185.svg"}, {"path": "page1-172.svg"}, {"path": "page5-26.svg"}, {"path": "page2-190.svg"}, {"path": "page7-15.svg"}, {"path": "page1-128.svg"}, {"path": "page6-166.svg"}, {"path": "page6-228.svg"}, {"path": "page2-114.svg"}, {"path": "page6-167.svg"}], "chat_mode": "single-utterance-unidirectional"}, {"context": ["page6-185.svg", "page1-172.svg", "page5-26.svg", "page2-190.svg", "page7-15.svg", "page1-128.svg", "page6-166.svg", "page6-228.svg", "page2-114.svg", "page6-167.svg"], "target": "page5-26.svg", "target_snd_class": "low", "roles": ["listener", "speaker"], "tangrams_order": [[2, 9, 7, 8, 6, 3, 0, 4, 5, 1], [3, 7, 8, 6, 0, 4, 9, 5, 2, 1]], "block": 3, "controled": false, "images": [{"path": "page6-185.svg"}, {"path": "page1-172.svg"}, {"path": "page5-26.svg"}, {"path": "page2-190.svg"}, {"path": "page7-15.svg"}, {"path": "page1-128.svg"}, {"path": "page6-166.svg"}, {"path": "page6-228.svg"}, {"path": "page2-114.svg"}, {"path": "page6-167.svg"}], "chat_mode": "single-utterance-unidirectional"}, {"context": ["page6-185.svg", "page1-172.svg", "page5-26.svg", "page2-190.svg", "page7-15.svg", "page1-128.svg", "page6-166.svg", "page6-228.svg", "page2-114.svg", "page6-167.svg"], "target": "page2-114.svg", "target_snd_class": "high", "roles": ["listener", "speaker"], "tangrams_order": [[2, 9, 7, 8, 6, 3, 0, 4, 5, 1], [3, 7, 8, 6, 0, 4, 9, 5, 2, 1]], "block": 3, "controled": false, "images": [{"path": "page6-185.svg"}, {"path": "page1-172.svg"}, {"path": "page5-26.svg"}, {"path": "page2-190.svg"}, {"path": "page7-15.svg"}, {"path": "page1-128.svg"}, {"path": "page6-166.svg"}, {"path": "page6-228.svg"}, {"path": "page2-114.svg"}, {"path": "page6-167.svg"}], "chat_mode": "single-utterance-unidirectional"}, {"context": ["page6-185.svg", "page1-172.svg", "page5-26.svg", "page2-190.svg", "page7-15.svg", "page1-128.svg", "page6-166.svg", "page6-228.svg", "page2-114.svg", "page6-167.svg"], "target": "page6-166.svg", "target_snd_class": "high", "roles": ["listener", "speaker"], "tangrams_order": [[2, 9, 7, 8, 6, 3, 0, 4, 5, 1], [3, 7, 8, 6, 0, 4, 9, 5, 2, 1]], "block": 3, "controled": false, "images": [{"path": "page6-185.svg"}, {"path": "page1-172.svg"}, {"path": "page5-26.svg"}, {"path": "page2-190.svg"}, {"path": "page7-15.svg"}, {"path": "page1-128.svg"}, {"path": "page6-166.svg"}, {"path": "page6-228.svg"}, {"path": "page2-114.svg"}, {"path": "page6-167.svg"}], "chat_mode": "single-utterance-unidirectional"}, {"context": ["page6-185.svg", "page1-172.svg", "page5-26.svg", "page2-190.svg", "page7-15.svg", "page1-128.svg", "page6-166.svg", "page6-228.svg", "page2-114.svg", "page6-167.svg"], "target": "page2-190.svg", "target_snd_class": null, "roles": ["listener", "speaker"], "tangrams_order": [[2, 9, 7, 8, 6, 3, 0, 4, 5, 1], [3, 7, 8, 6, 0, 4, 9, 5, 2, 1]], "block": 3, "controled": true, "images": [{"path": "page6-185.svg"}, {"path": "page1-172.svg"}, {"path": "page5-26.svg"}, {"path": "page2-190.svg"}, {"path": "page7-15.svg"}, {"path": "page1-128.svg"}, {"path": "page6-166.svg"}, {"path": "page6-228.svg"}, {"path": "page2-114.svg"}, {"path": "page6-167.svg"}], "chat_mode": "single-utterance-unidirectional"}, {"context": ["page6-185.svg", "page1-172.svg", "page5-26.svg", "page2-190.svg", "page7-15.svg", "page1-128.svg", "page6-166.svg", "page6-228.svg", "page2-114.svg", "page6-167.svg"], "target": "page6-185.svg", "target_snd_class": "low", "roles": ["listener", "speaker"], "tangrams_order": [[2, 9, 7, 8, 6, 3, 0, 4, 5, 1], [3, 7, 8, 6, 0, 4, 9, 5, 2, 1]], "block": 3, "controled": false, "images": [{"path": "page6-185.svg"}, {"path": "page1-172.svg"}, {"path": "page5-26.svg"}, {"path": "page2-190.svg"}, {"path": "page7-15.svg"}, {"path": "page1-128.svg"}, {"path": "page6-166.svg"}, {"path": "page6-228.svg"}, {"path": "page2-114.svg"}, {"path": "page6-167.svg"}], "chat_mode": "single-utterance-unidirectional"}, {"context": ["page6-185.svg", "page1-172.svg", "page5-26.svg", "page2-190.svg", "page7-15.svg", "page1-128.svg", "page6-166.svg", "page6-228.svg", "page2-114.svg", "page6-167.svg"], "target": "page7-15.svg", "target_snd_class": "low", "roles": ["listener", "speaker"], "tangrams_order": [[2, 9, 7, 8, 6, 3, 0, 4, 5, 1], [3, 7, 8, 6, 0, 4, 9, 5, 2, 1]], "block": 3, "controled": false, "images": [{"path": "page6-185.svg"}, {"path": "page1-172.svg"}, {"path": "page5-26.svg"}, {"path": "page2-190.svg"}, {"path": "page7-15.svg"}, {"path": "page1-128.svg"}, {"path": "page6-166.svg"}, {"path": "page6-228.svg"}, {"path": "page2-114.svg"}, {"path": "page6-167.svg"}], "chat_mode": "single-utterance-unidirectional"}, {"context": ["page6-185.svg", "page1-172.svg", "page5-26.svg", "page2-190.svg", "page7-15.svg", "page1-128.svg", "page6-166.svg", "page6-228.svg", "page2-114.svg", "page6-167.svg"], "target": "page2-114.svg", "target_snd_class": "high", "roles": ["speaker", "listener"], "tangrams_order": [[3, 7, 8, 6, 0, 4, 9, 5, 2, 1], [2, 9, 7, 8, 6, 3, 0, 4, 5, 1]], "block": 4, "controled": false, "images": [{"path": "page6-185.svg"}, {"path": "page1-172.svg"}, {"path": "page5-26.svg"}, {"path": "page2-190.svg"}, {"path": "page7-15.svg"}, {"path": "page1-128.svg"}, {"path": "page6-166.svg"}, {"path": "page6-228.svg"}, {"path": "page2-114.svg"}, {"path": "page6-167.svg"}], "chat_mode": "single-utterance-unidirectional"}, {"context": ["page6-185.svg", "page1-172.svg", "page5-26.svg", "page2-190.svg", "page7-15.svg", "page1-128.svg", "page6-166.svg", "page6-228.svg", "page2-114.svg", "page6-167.svg"], "target": "page6-166.svg", "target_snd_class": "high", "roles": ["speaker", "listener"], "tangrams_order": [[3, 7, 8, 6, 0, 4, 9, 5, 2, 1], [2, 9, 7, 8, 6, 3, 0, 4, 5, 1]], "block": 4, "controled": false, "images": [{"path": "page6-185.svg"}, {"path": "page1-172.svg"}, {"path": "page5-26.svg"}, {"path": "page2-190.svg"}, {"path": "page7-15.svg"}, {"path": "page1-128.svg"}, {"path": "page6-166.svg"}, {"path": "page6-228.svg"}, {"path": "page2-114.svg"}, {"path": "page6-167.svg"}], "chat_mode": "single-utterance-unidirectional"}, {"context": ["page6-185.svg", "page1-172.svg", "page5-26.svg", "page2-190.svg", "page7-15.svg", "page1-128.svg", "page6-166.svg", "page6-228.svg", "page2-114.svg", "page6-167.svg"], "target": "page5-26.svg", "target_snd_class": "low", "roles": ["speaker", "listener"], "tangrams_order": [[3, 7, 8, 6, 0, 4, 9, 5, 2, 1], [2, 9, 7, 8, 6, 3, 0, 4, 5, 1]], "block": 4, "controled": false, "images": [{"path": "page6-185.svg"}, {"path": "page1-172.svg"}, {"path": "page5-26.svg"}, {"path": "page2-190.svg"}, {"path": "page7-15.svg"}, {"path": "page1-128.svg"}, {"path": "page6-166.svg"}, {"path": "page6-228.svg"}, {"path": "page2-114.svg"}, {"path": "page6-167.svg"}], "chat_mode": "single-utterance-unidirectional"}, {"context": ["page6-185.svg", "page1-172.svg", "page5-26.svg", "page2-190.svg", "page7-15.svg", "page1-128.svg", "page6-166.svg", "page6-228.svg", "page2-114.svg", "page6-167.svg"], "target": "page6-228.svg", "target_snd_class": null, "roles": ["listener", "speaker"], "tangrams_order": [[2, 9, 7, 8, 6, 3, 0, 4, 5, 1], [3, 7, 8, 6, 0, 4, 9, 5, 2, 1]], "block": 4, "controled": true, "images": [{"path": "page6-185.svg"}, {"path": "page1-172.svg"}, {"path": "page5-26.svg"}, {"path": "page2-190.svg"}, {"path": "page7-15.svg"}, {"path": "page1-128.svg"}, {"path": "page6-166.svg"}, {"path": "page6-228.svg"}, {"path": "page2-114.svg"}, {"path": "page6-167.svg"}], "chat_mode": "single-utterance-unidirectional"}, {"context": ["page6-185.svg", "page1-172.svg", "page5-26.svg", "page2-190.svg", "page7-15.svg", "page1-128.svg", "page6-166.svg", "page6-228.svg", "page2-114.svg", "page6-167.svg"], "target": "page7-15.svg", "target_snd_class": "low", "roles": ["speaker", "listener"], "tangrams_order": [[3, 7, 8, 6, 0, 4, 9, 5, 2, 1], [2, 9, 7, 8, 6, 3, 0, 4, 5, 1]], "block": 4, "controled": false, "images": [{"path": "page6-185.svg"}, {"path": "page1-172.svg"}, {"path": "page5-26.svg"}, {"path": "page2-190.svg"}, {"path": "page7-15.svg"}, {"path": "page1-128.svg"}, {"path": "page6-166.svg"}, {"path": "page6-228.svg"}, {"path": "page2-114.svg"}, {"path": "page6-167.svg"}], "chat_mode": "single-utterance-unidirectional"}, {"context": ["page6-185.svg", "page1-172.svg", "page5-26.svg", "page2-190.svg", "page7-15.svg", "page1-128.svg", "page6-166.svg", "page6-228.svg", "page2-114.svg", "page6-167.svg"], "target": "page6-185.svg", "target_snd_class": "low", "roles": ["speaker", "listener"], "tangrams_order": [[3, 7, 8, 6, 0, 4, 9, 5, 2, 1], [2, 9, 7, 8, 6, 3, 0, 4, 5, 1]], "block": 4, "controled": false, "images": [{"path": "page6-185.svg"}, {"path": "page1-172.svg"}, {"path": "page5-26.svg"}, {"path": "page2-190.svg"}, {"path": "page7-15.svg"}, {"path": "page1-128.svg"}, {"path": "page6-166.svg"}, {"path": "page6-228.svg"}, {"path": "page2-114.svg"}, {"path": "page6-167.svg"}], "chat_mode": "single-utterance-unidirectional"}]}